scout/__init__.py
scout/cli.py
scout/commands/__init__.py
scout/commands/help.py
scout/commands/jump.py
scout/commands/list.py
scout/functions/smart_predict.py
scout/shell/scout.sh
scout_cli-0.11.0.data/data/share/scout/scout.sh
scout_cli-0.11.0.dist-info/METADATA
scout_cli-0.11.0.dist-info/WHEEL
scout_cli-0.11.0.dist-info/entry_points.txt
scout_cli-0.11.0.dist-info/RECORD
