Metadata-Version: 2.4
Name: scout-cli
Version: 0.11.0
Summary: A modern, intuitive alternative to ls command with smart directory prediction
Author: Andrew Wade
Requires-Python: >=3.7
Requires-Dist: click>=8.0.0
Requires-Dist: numpy>=1.21.0
Requires-Dist: python-levenshtein>=0.21.0
Requires-Dist: rich>=10.0.0
Requires-Dist: scikit-learn>=1.0.2
Requires-Dist: thefuzz>=0.19.0
Requires-Dist: typer>=0.9.0
